claude_cto/__init__.py
claude_cto/cli/__init__.py
claude_cto/cli/config.py
claude_cto/cli/main.py
claude_cto/core/__init__.py
claude_cto/core/database.py
claude_cto/core/error_codes.py
claude_cto/core/executor.py
claude_cto/core/updater.py
claude_cto/mcp/__init__.py
claude_cto/mcp/auto_config.py
claude_cto/mcp/enhanced_proxy.py
claude_cto/mcp/factory.py
claude_cto/mcp/orchestration_tool.py
claude_cto/mcp/proxy.py
claude_cto/mcp/standalone.py
claude_cto/migrations/__init__.py
claude_cto/migrations/manager.py
claude_cto/server/__init__.py
claude_cto/server/circuit_breaker_persistence.py
claude_cto/server/config.py
claude_cto/server/crud.py
claude_cto/server/database.py
claude_cto/server/error_handler.py
claude_cto/server/executor.py
claude_cto/server/log_formatter.py
claude_cto/server/main.py
claude_cto/server/memory_monitor.py
claude_cto/server/models.py
claude_cto/server/notification.py
claude_cto/server/orchestrator.py
claude_cto/server/path_utils.py
claude_cto/server/port_manager.py
claude_cto/server/process_registry.py
claude_cto/server/recovery.py
claude_cto/server/retry_handler.py
claude_cto/server/server_lock.py
claude_cto/server/server_logger.py
claude_cto/server/signal_handler.py
claude_cto/server/subprocess_manager.py
claude_cto/server/task_logger.py
claude_cto/server/task_runner.py
claude_cto-0.20.1.dist-info/METADATA
claude_cto-0.20.1.dist-info/WHEEL
claude_cto-0.20.1.dist-info/entry_points.txt
claude_cto-0.20.1.dist-info/licenses/LICENSE
claude_cto-0.20.1.dist-info/RECORD
