Metadata-Version: 2.4
Name: claude-cto
Version: 0.20.1
Summary: Fire-and-forget task execution system for Claude Code SDK with CLI and MCP interfaces
Project-URL: Homepage, https://github.com/yigitkonur/claude-cto
Project-URL: Repository, https://github.com/yigitkonur/claude-cto
Project-URL: Documentation, https://github.com/yigitkonur/claude-cto/blob/main/README.md
Project-URL: Bug Tracker, https://github.com/yigitkonur/claude-cto/issues
Project-URL: Changelog, https://github.com/yigitkonur/claude-cto/blob/main/CHANGELOG.md
Project-URL: MCP Documentation, https://github.com/yigitkonur/claude-cto/blob/main/MCP_README.md
Project-URL: Smithery, https://smithery.ai/@yigitkonur/claude-cto
Author-email: Yigit Konur <yigit@thinkbuddy.ai>
License: MIT
License-File: LICENSE
Keywords: ai,anthropic,automation,claude,cli,mcp,task-queue
Classifier: Development Status :: 4 - Beta
Classifier: Environment :: Console
Classifier: Framework :: FastAPI
Classifier: Intended Audience :: Developers
Classifier: License :: OSI Approved :: MIT License
Classifier: Operating System :: OS Independent
Classifier: Programming Language :: Python :: 3
Classifier: Programming Language :: Python :: 3.10
Classifier: Programming Language :: Python :: 3.11
Classifier: Programming Language :: Python :: 3.12
Classifier: Topic :: Scientific/Engineering :: Artificial Intelligence
Classifier: Topic :: Software Development :: Libraries :: Python Modules
Requires-Python: >=3.10
Requires-Dist: alembic>=1.13.0
Requires-Dist: claude-code-sdk>=0.0.19
Requires-Dist: fastmcp>=2.0.0
Requires-Dist: httpx>=0.25.0
Requires-Dist: psutil>=5.9.0
Requires-Dist: sqlmodel>=0.0.14
Requires-Dist: typer[rich]>=0.12.0
Provides-Extra: dev
Requires-Dist: black>=25.1.0; extra == 'dev'
Requires-Dist: pytest-asyncio>=0.21.0; extra == 'dev'
Requires-Dist: pytest>=7.0.0; extra == 'dev'
Requires-Dist: ruff>=0.12.9; extra == 'dev'
Provides-Extra: full
Requires-Dist: fastapi>=0.100.0; extra == 'full'
Requires-Dist: uvicorn[standard]>=0.23.0; extra == 'full'
Provides-Extra: mcp
Provides-Extra: server
Requires-Dist: fastapi>=0.100.0; extra == 'server'
Requires-Dist: uvicorn[standard]>=0.23.0; extra == 'server'
